pyisckea/__init__.py
pyisckea/daemons/__init__.py
pyisckea/daemons/ctrlagent.py
pyisckea/daemons/ddns.py
pyisckea/daemons/dhcp4.py
pyisckea/daemons/dhcp6.py
pyisckea/exceptions.py
pyisckea/kea.py
pyisckea/models/__init__.py
pyisckea/models/ctrlagent/__init__.py
pyisckea/models/ctrlagent/config.py
pyisckea/models/dhcp4/__init__.py
pyisckea/models/dhcp4/client_class.py
pyisckea/models/dhcp4/config.py
pyisckea/models/dhcp4/lease.py
pyisckea/models/dhcp4/reservation.py
pyisckea/models/dhcp4/shared_network.py
pyisckea/models/dhcp4/subnet.py
pyisckea/models/dhcp6/__init__.py
pyisckea/models/dhcp6/client_class.py
pyisckea/models/dhcp6/config.py
pyisckea/models/dhcp6/lease.py
pyisckea/models/dhcp6/pd_pool.py
pyisckea/models/dhcp6/reservation.py
pyisckea/models/dhcp6/server_id.py
pyisckea/models/dhcp6/shared_network.py
pyisckea/models/dhcp6/subnet.py
pyisckea/models/enums.py
pyisckea/models/generic/__init__.py
pyisckea/models/generic/api_response.py
pyisckea/models/generic/authentication.py
pyisckea/models/generic/base.py
pyisckea/models/generic/client_class.py
pyisckea/models/generic/config.py
pyisckea/models/generic/control_socket.py
pyisckea/models/generic/daemon.py
pyisckea/models/generic/database.py
pyisckea/models/generic/dhcp_common.py
pyisckea/models/generic/dhcp_ddns.py
pyisckea/models/generic/dhcp_queue_control.py
pyisckea/models/generic/high_availability.py
pyisckea/models/generic/hook.py
pyisckea/models/generic/lease.py
pyisckea/models/generic/logger.py
pyisckea/models/generic/multi_threading.py
pyisckea/models/generic/option_data.py
pyisckea/models/generic/option_def.py
pyisckea/models/generic/pool.py
pyisckea/models/generic/relay.py
pyisckea/models/generic/remote_map.py
pyisckea/models/generic/remote_server.py
pyisckea/models/generic/reservation.py
pyisckea/models/generic/sanity_check.py
pyisckea/models/generic/shared_network.py
pyisckea/models/generic/sockets.py
pyisckea/models/generic/status.py
pyisckea/models/generic/subnet.py
pyisckea/parsers/__init__.py
pyisckea-0.9.2.dist-info/LICENSE
pyisckea-0.9.2.dist-info/METADATA
pyisckea-0.9.2.dist-info/WHEEL
pyisckea-0.9.2.dist-info/RECORD
