Metadata-Version: 2.3
Name: pyisckea
Version: 0.9.2
Summary: Wrapper around requests module to query ISC Kea DHCP API Daemons (ctrlagent, dhcp4, dhcp6, ddns)
License: Apache 2.0
Author: Brandon Spendlove
Author-email: brandon-spendlove@hotmail.co.uk
Requires-Python: >=3.10,<4.0
Classifier: License :: Other/Proprietary License
Classifier: Programming Language :: Python :: 3
Classifier: Programming Language :: Python :: 3.10
Classifier: Programming Language :: Python :: 3.11
Classifier: Programming Language :: Python :: 3.12
Classifier: Programming Language :: Python :: 3.13
Requires-Dist: httpx (>=0.28.1,<0.29.0)
Requires-Dist: pydantic (>=2.10.6,<3.0.0)
